__init__.py
fhir/__init__.py
fhir/smart/__init__.py
fhir/smart/scopes/__init__.py
fhir.smart.scopes-0.0.2.dist-info/LICENSE
fhir.smart.scopes-0.0.2.dist-info/METADATA
fhir.smart.scopes-0.0.2.dist-info/WHEEL
fhir.smart.scopes-0.0.2.dist-info/top_level.txt
fhir.smart.scopes-0.0.2.dist-info/RECORD
