Metadata-Version: 2.1
Name: fhir.smart.scopes
Version: 0.0.2
Summary: A simple wrapper around SMART on FHIR scopes to treat them as Python sets.
Author-email: Katsch Florian <florian.katsch@dhp.lbg.ac.at>
Project-URL: Homepage, https://github.com/thisismexp/fhir.smart.scopes
Project-URL: Bug Tracker, https://github.com/thisismexp/fhir.smart.scopes/issues
Classifier: Programming Language :: Python :: 3
Classifier: License :: OSI Approved :: MIT License
Classifier: Operating System :: OS Independent
Classifier: Intended Audience :: Healthcare Industry
Classifier: Natural Language :: English
Requires-Python: >=3.7
License-File: LICENSE
